cjm_fasthtml_jsonschema/__init__.py
cjm_fasthtml_jsonschema/_modidx.py
cjm_fasthtml_jsonschema/components/__init__.py
cjm_fasthtml_jsonschema/components/fields.py
cjm_fasthtml_jsonschema/core/__init__.py
cjm_fasthtml_jsonschema/core/parser.py
cjm_fasthtml_jsonschema/core/types.py
cjm_fasthtml_jsonschema/generators/__init__.py
cjm_fasthtml_jsonschema/generators/form.py
cjm_fasthtml_jsonschema-0.0.6.dist-info/licenses/LICENSE
cjm_fasthtml_jsonschema-0.0.6.dist-info/METADATA
cjm_fasthtml_jsonschema-0.0.6.dist-info/WHEEL
cjm_fasthtml_jsonschema-0.0.6.dist-info/entry_points.txt
cjm_fasthtml_jsonschema-0.0.6.dist-info/top_level.txt
cjm_fasthtml_jsonschema-0.0.6.dist-info/RECORD
